Metadata-Version: 2.1
Name: irhm
Version: 0.1.0
Summary: IR-Drop Heatmap
Home-page: https://github.com/yeungchie/irhm
Author: YEUNGCHIE
Author-email: im.yeung.chie@outlook.com
Keywords: irhm,ic,ir,drop,heatmap,totem
Classifier: Development Status :: 3 - Alpha
Classifier: Intended Audience :: Developers
Classifier: Programming Language :: Python :: 3
Classifier: Programming Language :: Python :: 3.8
Classifier: Programming Language :: Python :: 3.12
Classifier: License :: OSI Approved :: Apache Software License
Classifier: Operating System :: Unix
Requires-Python: >=3.8
Requires-Dist: numpy
Requires-Dist: matplotlib
Requires-Dist: seaborn
Requires-Dist: PySide6
